excel_convert_xml/TestCase_IHG_Adapter.xls
excel_convert_xml/__init__.py
excel_convert_xml/comm_xml.py
excel_convert_xml/config.ini
excel_convert_xml/excel.py
excel_convert_xml-1.0.2.dist-info/METADATA
excel_convert_xml-1.0.2.dist-info/WHEEL
excel_convert_xml-1.0.2.dist-info/top_level.txt
excel_convert_xml-1.0.2.dist-info/zip-safe
excel_convert_xml-1.0.2.dist-info/RECORD
