Metadata-Version: 2.1
Name: excel-convert-xml
Version: 1.0.2
Summary: excel testcase convert testrail xml file
Home-page: https://github.com
Author: jianzhong.zhou
Author-email: 1329870572@qq.com
License: MIT
Platform: UNKNOWN
Classifier: License :: OSI Approved :: MIT License
Classifier: Programming Language :: Python
Classifier: Intended Audience :: Developers
